um982/UM982.py
um982/__init__.py
um982_driver-0.2.1.dist-info/METADATA
um982_driver-0.2.1.dist-info/WHEEL
um982_driver-0.2.1.dist-info/top_level.txt
um982_driver-0.2.1.dist-info/RECORD
