Metadata-Version: 2.1
Name: um982-driver
Version: 0.2.1
Summary: - Driver for UNICORECOMM UM982/UM980 GPS
Project-URL: Documentation, https://github.com/sunshineharry/UM982Driver/
Project-URL: Code, https://github.com/sunshineharry/UM982Driver/
Requires-Dist: numpy
Requires-Dist: pyproj
